{
	"failure_code": 8804,
	"details": [
		{
			"failure_code": 8804,
			"sub_system_type": "Host",
			"sub_system_id": "65938f9b-9e7f-49ea-b627-96e13aec8a16",
			"state": "failed",
			"failure_message": " Host configuration: Failed to handle the HostConfig reply message from host 65938f9b-9e7f-49ea-b627-96e13aec8a16 [TN=TransportNode/65938f9b-9e7f-49ea-b627-96e13aec8a16]. Reason: RPC request timed out."
		}
	],
	"state": "failed",
	"failure_message": "Host configuration failed.",
	"transport_node_id": "65938f9b-9e7f-49ea-b627-96e13aec8a16",
	"maintenance_mode_state": "DISABLED"
}
